manim_timeline/__init__.py
manim_timeline/axes.py
manim_timeline/graph.py
manim_timeline/quotes.py
manim_timeline/timeline.py
manim_timeline/timeline_helper.py
manim_timeline/utils.py
manim_timeline-0.0.3.dist-info/METADATA
manim_timeline-0.0.3.dist-info/WHEEL
manim_timeline-0.0.3.dist-info/licenses/LICENSE
manim_timeline-0.0.3.dist-info/RECORD
