Metadata-Version: 2.3
Name: manim-timeline
Version: 0.0.3
Summary: A seamless and elegant timeline for rapid presentation of related literature.
Project-URL: Homepage, https://github.com/johnHostetter/manim-timeline
Project-URL: Issues, https://github.com/johnHostetter/manim-timeline/issues
Author-email: John Wesley Hostetter <jhostetter16@gmail.com>
License-File: LICENSE
Classifier: License :: OSI Approved :: MIT License
Classifier: Operating System :: OS Independent
Classifier: Programming Language :: Python :: 3
Requires-Python: >=3.9
